LICENSE
MANIFEST.in
README.md
setup.py
mbed_flasher/__init__.py
mbed_flasher/common.py
mbed_flasher/daplink_errors.py
mbed_flasher/erase.py
mbed_flasher/flash.py
mbed_flasher/main.py
mbed_flasher/mbed_common.py
mbed_flasher/reset.py
mbed_flasher/return_codes.py
mbed_flasher.egg-info/PKG-INFO
mbed_flasher.egg-info/SOURCES.txt
mbed_flasher.egg-info/dependency_links.txt
mbed_flasher.egg-info/entry_points.txt
mbed_flasher.egg-info/requires.txt
mbed_flasher.egg-info/top_level.txt
mbed_flasher/flashers/FlasherAtmelAt.py
mbed_flasher/flashers/FlasherBase.py
mbed_flasher/flashers/FlasherJLink.py
mbed_flasher/flashers/FlasherMbed.py
mbed_flasher/flashers/FlasherST.py
mbed_flasher/flashers/__init__.py
mbed_flasher/flashers/enhancedserial.py
test/hardware/__init__.py
test/hardware/test_cliapi.py
test/hardware/test_erase.py
test/hardware/test_flash.py
test/hardware/test_helper.py
test/hardware/test_main.py
test/hardware/test_reset.py
test/hardware/test_verify_flash.py
test/non_hardware/__init__.py
test/non_hardware/test_cliapi.py
test/non_hardware/test_common.py
test/non_hardware/test_erase.py
test/non_hardware/test_flash.py
test/non_hardware/test_flasherbase.py
test/non_hardware/test_flasherjlink.py
test/non_hardware/test_flasherstlink.py
test/non_hardware/test_main.py
test/non_hardware/test_mbed_common.py
test/non_hardware/test_reset.py