Metadata-Version: 1.2
Name: mbed-flasher
Version: 0.9.1
Summary: mbed-flasher
Home-page: https://github.com/ARMmbed/mbed-flasher
Author: Jussi Vatjus-Anttila
Author-email: Jussi.Vatjus-Anttila@arm.com
Maintainer: Jussi Vatjus-Anttila
Maintainer-email: Jussi.Vatjus-Anttila@arm.com
License: Copyright 2016 ARM Limited
